dso/__init__.py
dso/_compile_config.py
dso/_get_config.py
dso/_lint.py
dso/_logging.py
dso/_metadata.py
dso/_quarto.py
dso/_templates.py
dso/_util.py
dso/_watermark.py
dso/api.py
dso/pandocfilter.py
dso/assets/__init__.py
dso/assets/open_sans.ttf
dso/cli/__init__.py
dso/cli/_create.py
dso/cli/_exec.py
dso/templates/.gitignore
dso/templates/LICENSE
dso/templates/README.md
dso/templates/__init__.py
dso/templates/index.json
dso/templates/schema.json
dso/templates/folder/__init__.py
dso/templates/folder/default/dvc.yaml
dso/templates/folder/default/params.in.yaml
dso/templates/init/__init__.py
dso/templates/init/default/.dvcignore
dso/templates/init/default/.editorconfig
dso/templates/init/default/.gitattributes
dso/templates/init/default/.gitignore
dso/templates/init/default/.pre-commit-config.yaml
dso/templates/init/default/README.md
dso/templates/init/default/dvc.yaml
dso/templates/init/default/params.in.yaml
dso/templates/init/default/pyproject.toml
dso/templates/init/default/.dvc/.gitignore
dso/templates/init/default/.dvc/config
dso/templates/stage/__init__.py
dso/templates/stage/bash/.gitignore
dso/templates/stage/bash/README.md
dso/templates/stage/bash/dvc.yaml
dso/templates/stage/bash/params.in.yaml
dso/templates/stage/bash/input/.gitkeeptemplate
dso/templates/stage/bash/output/.gitkeeptemplate
dso/templates/stage/quarto_ipynb/.gitignore
dso/templates/stage/quarto_ipynb/README.md
dso/templates/stage/quarto_ipynb/dvc.yaml
dso/templates/stage/quarto_ipynb/params.in.yaml
dso/templates/stage/quarto_ipynb/input/.gitkeeptemplate
dso/templates/stage/quarto_ipynb/output/.gitkeeptemplate
dso/templates/stage/quarto_ipynb/src/.gitignore
dso/templates/stage/quarto_ipynb/src/{{ name }}.ipynb
dso/templates/stage/quarto_py/.gitignore
dso/templates/stage/quarto_py/README.md
dso/templates/stage/quarto_py/dvc.yaml
dso/templates/stage/quarto_py/params.in.yaml
dso/templates/stage/quarto_py/input/.gitkeeptemplate
dso/templates/stage/quarto_py/output/.gitkeeptemplate
dso_core-0.13.3.dist-info/METADATA
dso_core-0.13.3.dist-info/WHEEL
dso_core-0.13.3.dist-info/entry_points.txt
dso_core-0.13.3.dist-info/licenses/LICENSE
dso_core-0.13.3.dist-info/RECORD
