Metadata-Version: 2.4
Name: dso-core
Version: 0.13.3
Summary: Data Science Operations on top of dvc
Project-URL: Documentation, https://github.com/Boehringer-Ingelheim/dso
Project-URL: Home-page, https://github.com/Boehringer-Ingelheim/dso
Project-URL: Source, https://github.com/Boehringer-Ingelheim/dso
Author: Gregor Sturm, Thomas Schwarzl, Alexander Peltzer
Maintainer-email: Gregor Sturm <gregor.sturm@boehringer-ingelheim.com>
License:                    GNU LESSER GENERAL PUBLIC LICENSE
License-File: LICENSE
Classifier: Programming Language :: Python :: 3 :: Only
Classifier: Programming Language :: Python :: 3.11
Classifier: Programming Language :: Python :: 3.12
Classifier: Programming Language :: Python :: 3.13
Requires-Python: >=3.11
Requires-Dist: dvc
Requires-Dist: hiyapyco>=0.7
Requires-Dist: jinja2
Requires-Dist: panflute
Requires-Dist: pillow
Requires-Dist: pre-commit
Requires-Dist: pypdf
Requires-Dist: pyyaml
Requires-Dist: questionary>=2.1
Requires-Dist: rich
Requires-Dist: rich-click
Requires-Dist: ruamel-yaml
Requires-Dist: svgutils
Requires-Dist: uv
Provides-Extra: dev
Requires-Dist: hatch; extra == 'dev'
Requires-Dist: pre-commit; extra == 'dev'
Provides-Extra: doc
Requires-Dist: click-extra[sphinx]; extra == 'doc'
Requires-Dist: docutils!=0.18.*,!=0.19.*,>=0.8; extra == 'doc'
Requires-Dist: ipykernel; extra == 'doc'
Requires-Dist: ipython; extra == 'doc'
Requires-Dist: matplotlib; extra == 'doc'
Requires-Dist: myst-parser; extra == 'doc'
Requires-Dist: sphinx-autodoc-typehints; extra == 'doc'
Requires-Dist: sphinx-book-theme>=1; extra == 'doc'
Requires-Dist: sphinx-copybutton; extra == 'doc'
Requires-Dist: sphinx-design; extra == 'doc'
Requires-Dist: sphinx>=4; extra == 'doc'
Requires-Dist: sphinxcontrib-bibtex>=1; extra == 'doc'
Requires-Dist: sphinxext-opengraph; extra == 'doc'
Provides-Extra: test
Requires-Dist: coverage; extra == 'test'
Requires-Dist: freezegun; extra == 'test'
Requires-Dist: pytest; extra == 'test'
Requires-Dist: pytest-asyncio; extra == 'test'
Requires-Dist: pytest-cov; extra == 'test'
Requires-Dist: pytest-xdist; extra == 'test'
Requires-Dist: quarto; extra == 'test'
